{
  "aggregateCounts": {
    "corpora": 3,
    "encryptedArchives": 6,
    "encryptedAssets": 448,
    "entries": 3,
    "helperProfiles": 1,
    "keyProfiles": 2
  },
  "command": "vp run kaifuu:encrypted-readiness -- --private-manifest <private-encrypted-corpus-manifest>",
  "composedEvidenceHash": "sha256:15be4285b4ad81a30cc0f708ef82c3a231971c1a09ad6dcb08cb7df49a67a7d6",
  "composes": {
    "adapters": [
      {
        "engineFamily": "kirikiri_xp3",
        "id": "kirikiri-xp3"
      },
      {
        "engineFamily": "rpg_maker_mv_mz_media",
        "id": "rpg-maker-mv-mz-encrypted-media"
      },
      {
        "engineFamily": "siglus",
        "id": "siglus"
      }
    ],
    "artifacts": [
      {
        "artifactId": "kirikiri-xp3.helper-required.profile",
        "contentHash": "sha256:537026a8fdbf2534c38af509fe158b53d773b4e62063a2c5de6a8babcce3715a",
        "engineFamily": "kirikiri_xp3",
        "kind": "readiness_profile",
        "sourceNodeId": "KAIFUU-103"
      },
      {
        "artifactId": "kirikiri-xp3.positive.patch",
        "contentHash": "sha256:6a02e938a46c42f4e66a4f8123509325ca888fb233f47e76ab13f1bce26531cc",
        "engineFamily": null,
        "kind": "readiness_patch_evidence",
        "sourceNodeId": "KAIFUU-104"
      },
      {
        "artifactId": "kirikiri-xp3.positive.profile",
        "contentHash": "sha256:05bcafe501e4de05bf29388a1a333f5e4939424a1443885e3bea2a22b469792c",
        "engineFamily": "kirikiri_xp3",
        "kind": "readiness_profile",
        "sourceNodeId": "KAIFUU-103"
      },
      {
        "artifactId": "mv-mz-media.positive.profile",
        "contentHash": "sha256:36bf6606f2067d4092c96194884a5c8a964c7e7cecda33b5598b7d66e5c5b563",
        "engineFamily": "rpg_maker_mv_mz_media",
        "kind": "readiness_profile",
        "sourceNodeId": "KAIFUU-103"
      },
      {
        "artifactId": "siglus.missing-key.profile",
        "contentHash": "sha256:a5e7f141b3213a35aa38ad620a06c8f77cda6206a47120d132a98bbfdab318f0",
        "engineFamily": "siglus",
        "kind": "readiness_profile",
        "sourceNodeId": "KAIFUU-103"
      },
      {
        "artifactId": "siglus.positive.patch",
        "contentHash": "sha256:cb68c5544bedc74826cd8824081ff2fb352b4a3742c80ae471271ce64a0bba8f",
        "engineFamily": null,
        "kind": "readiness_patch_evidence",
        "sourceNodeId": "KAIFUU-104"
      },
      {
        "artifactId": "siglus.positive.profile",
        "contentHash": "sha256:f8c8982c5188f60528097edb924e8e206b45fb0b22f227ce126a67e26587b848",
        "engineFamily": "siglus",
        "kind": "readiness_profile",
        "sourceNodeId": "KAIFUU-103"
      }
    ],
    "commandEvidence": [
      {
        "command": "kaifuu readiness alpha-encrypted --fixtures-dir fixtures/kaifuu/alpha-encrypted",
        "id": "kaifuu-readiness-alpha-encrypted"
      },
      {
        "command": "kaifuu readiness validate --fixtures-dir fixtures/kaifuu/alpha-encrypted",
        "id": "kaifuu-readiness-validate"
      }
    ],
    "prerequisiteCounts": {
      "adapters": 3,
      "commandEvidence": 2,
      "coveredEngineFamilies": 3,
      "coveredSourceNodes": 2,
      "patchEvidence": 2,
      "readinessProfiles": 5,
      "surfaces": 2
    },
    "surfaces": [
      {
        "id": "alpha-encrypted-readiness-evidence",
        "sourceNodeId": "KAIFUU-104"
      },
      {
        "id": "packed-engine-readiness",
        "sourceNodeId": "KAIFUU-103"
      }
    ]
  },
  "corpusIds": ["corpus-alpha", "corpus-beta", "corpus-gamma"],
  "engineReadinessBins": {
    "kirikiri-xp3": {
      "blocked": 0,
      "detector_unknown": 0,
      "helper_required": 0,
      "key_missing": 0,
      "ready": 1,
      "unsupported_variant": 0
    },
    "rgss3-vx-ace": {
      "blocked": 0,
      "detector_unknown": 0,
      "helper_required": 0,
      "key_missing": 0,
      "ready": 0,
      "unsupported_variant": 0
    },
    "rpg-maker-mv": {
      "blocked": 0,
      "detector_unknown": 0,
      "helper_required": 0,
      "key_missing": 0,
      "ready": 0,
      "unsupported_variant": 0
    },
    "rpg-maker-mz": {
      "blocked": 0,
      "detector_unknown": 0,
      "helper_required": 0,
      "key_missing": 1,
      "ready": 0,
      "unsupported_variant": 0
    },
    "siglus": {
      "blocked": 0,
      "detector_unknown": 0,
      "helper_required": 1,
      "key_missing": 0,
      "ready": 0,
      "unsupported_variant": 0
    },
    "wolf": {
      "blocked": 0,
      "detector_unknown": 0,
      "helper_required": 0,
      "key_missing": 0,
      "ready": 0,
      "unsupported_variant": 0
    }
  },
  "entries": [
    {
      "corpusIdRedacted": "corpus-alpha",
      "encryptedArchives": 3,
      "encryptedAssets": 128,
      "engine": "kirikiri-xp3",
      "helperProfiles": 0,
      "keyProfiles": 1,
      "proofHash": "sha256:351634f2805d69a4ef69cee095cd590aa3828d1a9d5e6f988fcd93aaa388fe6d",
      "readinessBin": "ready"
    },
    {
      "corpusIdRedacted": "corpus-beta",
      "encryptedArchives": 1,
      "encryptedAssets": 64,
      "engine": "siglus",
      "helperProfiles": 1,
      "keyProfiles": 1,
      "proofHash": "sha256:f69b67a78bf6568ab9ecdadff5bc49952cdb2861fea44b635bce3e877af7a919",
      "readinessBin": "helper_required"
    },
    {
      "corpusIdRedacted": "corpus-gamma",
      "encryptedArchives": 2,
      "encryptedAssets": 256,
      "engine": "rpg-maker-mz",
      "helperProfiles": 0,
      "keyProfiles": 0,
      "proofHash": null,
      "readinessBin": "key_missing"
    }
  ],
  "generatedBy": "suite/scripts/kaifuu-encrypted-readiness-integration/run.mjs",
  "prerequisiteFindings": [],
  "reason": null,
  "schemaVersion": "itotori.kaifuu-encrypted-readiness-integration.v0.1",
  "status": "ok"
}
